agatesql/__init__.py
agatesql/table.py
agate_sql-0.7.2.dist-info/AUTHORS.rst
agate_sql-0.7.2.dist-info/COPYING
agate_sql-0.7.2.dist-info/METADATA
agate_sql-0.7.2.dist-info/WHEEL
agate_sql-0.7.2.dist-info/top_level.txt
agate_sql-0.7.2.dist-info/RECORD
