Metadata-Version: 2.1
Name: agate-sql
Version: 0.7.2
Summary: agate-sql adds SQL read/write support to agate.
Home-page: https://agate-sql.readthedocs.org/
Author: Christopher Groskopf
Author-email: chrisgroskopf@gmail.com
License: MIT
Classifier: Development Status :: 4 - Beta
Classifier: Intended Audience :: Developers
Classifier: Intended Audience :: Science/Research
Classifier: License :: OSI Approved :: MIT License
Classifier: Natural Language :: English
Classifier: Operating System :: OS Independent
Classifier: Programming Language :: Python
Classifier: Programming Language :: Python :: 3.8
Classifier: Programming Language :: Python :: 3.9
Classifier: Programming Language :: Python :: 3.10
Classifier: Programming Language :: Python :: 3.11
Classifier: Programming Language :: Python :: 3.12
Classifier: Programming Language :: Python :: Implementation :: CPython
Classifier: Programming Language :: Python :: Implementation :: PyPy
Classifier: Topic :: Scientific/Engineering :: Information Analysis
Classifier: Topic :: Software Development :: Libraries :: Python Modules
License-File: COPYING
License-File: AUTHORS.rst
Requires-Dist: agate>=1.5.0
Requires-Dist: sqlalchemy>=1.4
Provides-Extra: test
Requires-Dist: crate; extra == "test"
Requires-Dist: geojson; extra == "test"
Requires-Dist: pytest; extra == "test"
Requires-Dist: pytest-cov; extra == "test"
